{
    "worldIndex": 1,
    "levelIndex": 20,
    "minMoves": 27,
    "hintMoves": "L B B B R R R L L L F F F R F L B L F R F R F L F F R",
    "layout": [
        "-  -  -  -  -  -  -  -  w  w  8  -  -  -  -",
        "-  -  -  -  -  -  -  -  w  w  -  -  -  -  -",
        "-  -  -  -  -  -  -  -  w  w  1  -  -  -  -",
        "w  w  w  -  -  -  -  -  b3 b1 b1 -  -  -  -",
        "w  w  w  -  -  -  -  -  b3 b1 b1 -  -  -  -",
        "1  h2 1  1  b2 h3 1  1  w  1  w  -  -  -  -",
        "-  -  -  1  -  -  1  1  w  1  9  -  -  -  -",
        "-  -  -  1  1  1  1  -  1  1  1  -  -  -  -",
        "-  -  -  1  1  1  -  -  1  1  -  -  -  -  -",
        "-  -  -  -  -  -  -  -  1  1  1  1  1  h1 -"
    ]
}